<?xml version="1.0" encoding="UTF-8"?><record_update table="sp_instance">
    <sp_instance action="INSERT_OR_UPDATE">
        <active>true</active>
        <class_name/>
        <color>default</color>
        <css/>
        <glyph/>
        <id/>
        <order>0</order>
        <roles/>
        <short_description/>
        <size>md</size>
        <sp_column display_value="2">c01669c4f4ee32007f44717f642a222f</sp_column>
        <sp_widget display_value="Form">fd1f4ec347730200ba13a5554ee490c0</sp_widget>
        <sys_class_name>sp_instance</sys_class_name>
        <sys_created_by>admin</sys_created_by>
        <sys_created_on>2017-05-05 03:33:41</sys_created_on>
        <sys_id>4bf2fbd1c7623200b0b0409b9b9763be</sys_id>
        <sys_mod_count>1</sys_mod_count>
        <sys_name/>
        <sys_package display_value="Reusable Widgets" source="x_snc_reusable_wid">cbefa4faf41232007f44717f642a22b4</sys_package>
        <sys_policy/>
        <sys_scope display_value="Reusable Widgets">cbefa4faf41232007f44717f642a22b4</sys_scope>
        <sys_update_name>sp_instance_4bf2fbd1c7623200b0b0409b9b9763be</sys_update_name>
        <sys_updated_by>admin</sys_updated_by>
        <sys_updated_on>2017-05-08 19:34:28</sys_updated_on>
        <title/>
        <url/>
        <widget_parameters/>
    </sp_instance>
    <sys_translated_text action="delete_multiple" query="documentkey=4bf2fbd1c7623200b0b0409b9b9763be"/>
</record_update>
